testirequesti/Requesti.py
testirequesti/Responsi.py
testirequesti/__init__.py
testirequesti-0.0.1.dist-info/LICENSE
testirequesti-0.0.1.dist-info/METADATA
testirequesti-0.0.1.dist-info/WHEEL
testirequesti-0.0.1.dist-info/top_level.txt
testirequesti-0.0.1.dist-info/RECORD
