Metadata-Version: 2.1
Name: testirequesti
Version: 0.0.1
Summary: Mock requests for testing
Author-email: Uri <Uri.Cohen.Waisel@Gmail.com>
License: GNU GENERAL PUBLIC LICENSE
Project-URL: Homepage, https://github.com/UriCW/TestiPy
Project-URL: Issues, https://github.com/UriCW/TestiPy/issues
Classifier: Programming Language :: Python :: 3
Classifier: Operating System :: OS Independent
Requires-Python: >=3.8
License-File: LICENSE
Requires-Dist: requests >=2.31.0
